morebuiltins/__init__.py
morebuiltins/date.py
morebuiltins/download_python.py
morebuiltins/emails.py
morebuiltins/funcs.py
morebuiltins/ipc.py
morebuiltins/logs.py
morebuiltins/py.typed
morebuiltins/request.py
morebuiltins/shared_memory.py
morebuiltins/sqlite.py
morebuiltins/tk.py
morebuiltins/utils.py
morebuiltins/cmd/log_server.py
morebuiltins/cmd/parse_deps.py
morebuiltins/cmd/proxy_checker.py
morebuiltins/cmd/ui.py
morebuiltins/cmd/bin/_runner.py
morebuiltins/cmd/systemd/service.py
morebuiltins/cmd/systemd/timer.py
morebuiltins/snippets/event.py
morebuiltins/snippets/sql.py
morebuiltins/zipapps/__init__.py
morebuiltins/zipapps/__main__.py
morebuiltins/zipapps/activate_zipapps.py
morebuiltins/zipapps/download_python.py
morebuiltins/zipapps/ensure_zipapps.py.template
morebuiltins/zipapps/entry_point.py.template
morebuiltins/zipapps/freezing.py
morebuiltins/zipapps/main.py
morebuiltins-1.3.7.dist-info/entry_points.txt
morebuiltins-1.3.7.dist-info/licenses/LICENSE
morebuiltins-1.3.7.dist-info/WHEEL
morebuiltins-1.3.7.dist-info/METADATA
morebuiltins-1.3.7.dist-info/RECORD
