Metadata-Version: 2.4
Name: morebuiltins
Version: 1.3.7
Summary: Expanding Python's built-in functionalities to enable richer and more versatile work scenarios.
Author-email: ClericPy <clericpy@gmail.com>
Requires-Python: >=3.8
Classifier: License :: OSI Approved :: MIT License
License-File: LICENSE
Project-URL: Home, https://github.com/ClericPy/morebuiltins
